dayone_export/__init__.py
dayone_export/cli.py
dayone_export/compat.py
dayone_export/filters.py
dayone_export/mdx_autobold.py
dayone_export/mdx_hashtag.py
dayone_export/mdx_urlize.py
dayone_export/version.py
dayone_export/templates/default.html
dayone_export/templates/default.md
dayone_export/templates/default.org
dayone_export/templates/default.tex
dayone_export/templates/default.txt
dayone_export/templates/imgbase64.html
dayone_export-0.8.0.dist-info/DESCRIPTION.rst
dayone_export-0.8.0.dist-info/entry_points.txt
dayone_export-0.8.0.dist-info/METADATA
dayone_export-0.8.0.dist-info/metadata.json
dayone_export-0.8.0.dist-info/RECORD
dayone_export-0.8.0.dist-info/top_level.txt
dayone_export-0.8.0.dist-info/WHEEL
